symphra_event/__init__.py
symphra_event/decorators.py
symphra_event/exceptions.py
symphra_event/namespace.py
symphra_event/py.typed
symphra_event/types.py
symphra_event/utils.py
symphra_event/analysis/__init__.py
symphra_event/analysis/dependency.py
symphra_event/analysis/plugin.py
symphra_event/core/__init__.py
symphra_event/core/async_emitter.py
symphra_event/core/bus.py
symphra_event/core/emitter.py
symphra_event/debug/__init__.py
symphra_event/debug/plugin.py
symphra_event/debug/time_travel.py
symphra_event/execution/__init__.py
symphra_event/execution/parallel.py
symphra_event/execution/pipeline.py
symphra_event/execution/sequential.py
symphra_event/middleware/__init__.py
symphra_event/middleware/base.py
symphra_event/middleware/builtin.py
symphra_event/optimizer/__init__.py
symphra_event/optimizer/batch.py
symphra_event/optimizer/plugin.py
symphra_event/plugin/__init__.py
symphra_event/plugin/base.py
symphra_event/plugin/registry.py
symphra_event/transport/__init__.py
symphra_event/transport/plugin.py
symphra_event/transport/zero_copy.py
symphra_event-0.2.0.dist-info/METADATA
symphra_event-0.2.0.dist-info/WHEEL
symphra_event-0.2.0.dist-info/licenses/LICENSE
symphra_event-0.2.0.dist-info/RECORD
