Metadata-Version: 2.4
Name: symphra-event
Version: 0.2.0
Summary: High-performance event library for Python 3.11+
Author-email: Symphra <symphra@getaix.tech>
License: MIT
License-File: LICENSE
Keywords: emitter,event,observer,pubsub,signal
Classifier: Development Status :: 4 - Beta
Classifier: Intended Audience :: Developers
Classifier: License :: OSI Approved :: MIT License
Classifier: Programming Language :: Python :: 3.11
Classifier: Programming Language :: Python :: 3.12
Classifier: Typing :: Typed
Requires-Python: >=3.11
Provides-Extra: dev
Requires-Dist: mypy>=1.7; extra == 'dev'
Requires-Dist: pytest-benchmark>=4.0; extra == 'dev'
Requires-Dist: pytest-cov>=4.1; extra == 'dev'
Requires-Dist: pytest>=7.4; extra == 'dev'
Requires-Dist: ruff>=0.1.0; extra == 'dev'
